[
  {
    "descripcion": "Lugar extraordinario número 5",
    "puntos": 3
  },
  {
    "descripcion": "Lugar extraordinario número 38",
    "puntos": 1
  },
  {
    "descripcion": "Lugar extraordinario número 12",
    "puntos": 2
  },
  {
    "descripcion": "Lugar extraordinario número 16",
    "puntos": 2
  },
  {
    "descripcion": "Lugar extraordinario número 10",
    "puntos": 3
  },
  {
    "descripcion": "Lugar extraordinario número 7",
    "puntos": 3
  },
  {
    "descripcion": "Lugar extraordinario número 9",
    "puntos": 3
  },
  {
    "descripcion": "Lugar extraordinario número 11",
    "puntos": 2
  },
  {
    "descripcion": "Lugar extraordinario número 46",
    "puntos": 1
  },
  {
    "descripcion": "Lugar extraordinario número 48",
    "puntos": 1
  },
  {
    "descripcion": "Lugar extraordinario número 29",
    "puntos": 1
  },
  {
    "descripcion": "Lugar extraordinario número 21",
    "puntos": 2
  },
  {
    "descripcion": "Lugar extraordinario número 35",
    "puntos": 1
  },
  {
    "descripcion": "Lugar extraordinario número 26",
    "puntos": 1
  },
  {
    "descripcion": "Lugar extraordinario número 36",
    "puntos": 1
  },
  {
    "descripcion": "Lugar extraordinario número 33",
    "puntos": 1
  },
  {
    "descripcion": "Lugar extraordinario número 2",
    "puntos": 3
  },
  {
    "descripcion": "Lugar extraordinario número 17",
    "puntos": 2
  },
  {
    "descripcion": "Lugar extraordinario número 8",
    "puntos": 3
  },
  {
    "descripcion": "Lugar extraordinario número 18",
    "puntos": 2
  },
  {
    "descripcion": "Lugar extraordinario número 27",
    "puntos": 1
  },
  {
    "descripcion": "Lugar extraordinario número 24",
    "puntos": 2
  },
  {
    "descripcion": "Lugar extraordinario número 34",
    "puntos": 1
  },
  {
    "descripcion": "Lugar extraordinario número 6",
    "puntos": 3
  },
  {
    "descripcion": "Lugar extraordinario número 4",
    "puntos": 3
  },
  {
    "descripcion": "Lugar extraordinario número 15",
    "puntos": 2
  },
  {
    "descripcion": "Lugar extraordinario número 45",
    "puntos": 1
  },
  {
    "descripcion": "Lugar extraordinario número 40",
    "puntos": 1
  },
  {
    "descripcion": "Lugar extraordinario número 31",
    "puntos": 1
  },
  {
    "descripcion": "Lugar extraordinario número 3",
    "puntos": 3
  },
  {
    "descripcion": "Lugar extraordinario número 25",
    "puntos": 2
  },
  {
    "descripcion": "Lugar extraordinario número 19",
    "puntos": 2
  },
  {
    "descripcion": "Lugar extraordinario número 44",
    "puntos": 1
  },
  {
    "descripcion": "Lugar extraordinario número 37",
    "puntos": 1
  },
  {
    "descripcion": "Lugar extraordinario número 30",
    "puntos": 1
  },
  {
    "descripcion": "Lugar extraordinario número 13",
    "puntos": 2
  },
  {
    "descripcion": "Lugar extraordinario número 43",
    "puntos": 1
  },
  {
    "descripcion": "Lugar extraordinario número 47",
    "puntos": 1
  },
  {
    "descripcion": "Lugar extraordinario número 32",
    "puntos": 1
  },
  {
    "descripcion": "Lugar extraordinario número 22",
    "puntos": 2
  },
  {
    "descripcion": "Lugar extraordinario número 39",
    "puntos": 1
  },
  {
    "descripcion": "Lugar extraordinario número 14",
    "puntos": 2
  },
  {
    "descripcion": "Lugar extraordinario número 49",
    "puntos": 1
  },
  {
    "descripcion": "Lugar extraordinario número 20",
    "puntos": 2
  },
  {
    "descripcion": "Lugar extraordinario número 42",
    "puntos": 1
  },
  {
    "descripcion": "Lugar extraordinario número 41",
    "puntos": 1
  },
  {
    "descripcion": "Lugar extraordinario número 28",
    "puntos": 1
  },
  {
    "descripcion": "Lugar extraordinario número 1",
    "puntos": 3
  },
  {
    "descripcion": "Lugar extraordinario número 23",
    "puntos": 2
  },
  {
    "descripcion": "Lugar extraordinario número 50",
    "puntos": 1
  }
]